CHANGES.txt
LICENSE.txt
MANIFEST.in
README
README.md
dev-requirements.txt
requirements.txt
setup.cfg
setup.py
quora/__init__.py
quora/quora.py
quora/user.py
quora.egg-info/PKG-INFO
quora.egg-info/SOURCES.txt
quora.egg-info/dependency_links.txt
quora.egg-info/requires.txt
quora.egg-info/top_level.txt