Metadata-Version: 1.0
Name: quora
Version: 0.1.20.6
Summary: Fetches and parses data from Quora.
Home-page: https://github.com/csu/pyquora
Author: Christopher Su
Author-email: chris+py@christopher.su
License: UNKNOWN
Platform: UNKNOWN
